flavors2/__init__.py
flavors2/__version__.py
flavors2/core.py
flavors_squared-0.1.1.dist-info/licenses/LICENSE
flavors_squared-0.1.1.dist-info/METADATA
flavors_squared-0.1.1.dist-info/WHEEL
flavors_squared-0.1.1.dist-info/top_level.txt
flavors_squared-0.1.1.dist-info/RECORD
