Metadata-Version: 2.4
Name: flavors-squared
Version: 0.1.1
Summary: Fast and Lightweight Assessment of Variables for Optimally-Reduced Subsets towards Feature Learning Automation with Variable-Objective, Resource Scheduling
Author: Michael Mech
License: MIT License
Project-URL: Homepage, https://github.com/michaelmech/FLAVORS2
Project-URL: Issues, https://github.com/michaelmech/FLAVORS2/issues
Classifier: Programming Language :: Python :: 3
Classifier: License :: OSI Approved :: MIT License
Classifier: Operating System :: OS Independent
Requires-Python: >=3.9
License-File: LICENSE
Requires-Dist: numpy>=1.23
Requires-Dist: pandas>=1.5
Requires-Dist: scikit-learn>=1.2
Requires-Dist: joblib>=1.2
Provides-Extra: dev
Requires-Dist: pytest; extra == "dev"
Requires-Dist: black; extra == "dev"
Requires-Dist: ruff; extra == "dev"
Provides-Extra: viz
Requires-Dist: matplotlib; extra == "viz"
Dynamic: license-file
